meatpy/__init__.py
meatpy/events.py
meatpy/level.py
meatpy/lob.py
meatpy/market_event_handler.py
meatpy/market_processor.py
meatpy/message_reader.py
meatpy/timestamp.py
meatpy/trading_status.py
meatpy/types.py
meatpy/event_handlers/__init__.py
meatpy/event_handlers/lob_event_recorder.py
meatpy/event_handlers/lob_recorder.py
meatpy/event_handlers/ofi_recorder.py
meatpy/event_handlers/spot_measures_recorder.py
meatpy/iex_deep/__init__.py
meatpy/iex_deep/iex_deep_market_message.py
meatpy/iex_deep/iex_deep_market_processor.py
meatpy/iex_deep/iex_deep_message_reader.py
meatpy/itch2/__init__.py
meatpy/itch2/itch2_market_message.py
meatpy/itch2/itch2_market_processor.py
meatpy/itch2/itch2_message_reader.py
meatpy/itch3/__init__.py
meatpy/itch3/itch3_market_message.py
meatpy/itch3/itch3_market_processor.py
meatpy/itch3/itch3_message_reader.py
meatpy/itch4/__init__.py
meatpy/itch4/itch4_market_message.py
meatpy/itch4/itch4_market_processor.py
meatpy/itch4/itch4_message_reader.py
meatpy/itch41/__init__.py
meatpy/itch41/itch41_exec_trade_recorder.py
meatpy/itch41/itch41_market_message.py
meatpy/itch41/itch41_market_processor.py
meatpy/itch41/itch41_message_reader.py
meatpy/itch41/itch41_ofi_recorder.py
meatpy/itch41/itch41_order_event_recorder.py
meatpy/itch41/itch41_top_of_book_message_recorder.py
meatpy/itch41/itch41_writer.py
meatpy/itch50/__init__.py
meatpy/itch50/itch50_exec_trade_recorder.py
meatpy/itch50/itch50_market_message.py
meatpy/itch50/itch50_market_processor.py
meatpy/itch50/itch50_message_reader.py
meatpy/itch50/itch50_ofi_recorder.py
meatpy/itch50/itch50_order_event_recorder.py
meatpy/itch50/itch50_top_of_book_message_recorder.py
meatpy/itch50/itch50_writer.py
meatpy/writers/__init__.py
meatpy/writers/base_writer.py
meatpy/writers/csv_writer.py
meatpy/writers/parquet_writer.py
meatpy-0.4.0.dist-info/METADATA
meatpy-0.4.0.dist-info/WHEEL
meatpy-0.4.0.dist-info/licenses/LICENSE
meatpy-0.4.0.dist-info/RECORD
