Metadata-Version: 2.4
Name: meatpy
Version: 0.4.0
Summary: Read and process limit order book data
Project-URL: Repository, https://github.com/vgreg/MeatPy
Author-email: Vincent Grégoire <vincent.gregoire@hec.ca>, Charles Martineau <charles.martineau@utoronto.ca>
Maintainer-email: Vincent Grégoire <vincent.gregoire@hec.ca>
License: BSD-3-Clause
License-File: LICENSE
Classifier: Intended Audience :: Education
Classifier: Intended Audience :: Financial and Insurance Industry
Classifier: Topic :: Office/Business :: Financial
Classifier: Topic :: Scientific/Engineering :: Information Analysis
Requires-Python: >=3.11
Requires-Dist: pyarrow>=18.0.0
Provides-Extra: parquet
Requires-Dist: pyarrow>=10.0.0; extra == 'parquet'
